CS247-S1-3.v
module bcd(a,b,c,d,w,x,y,z);
  input a,b,c,d;
  output w,x,y,z;

  //Data-flow modelling
  assign w = b&c;
  assign x = b&~c | a&~b&c;
  assign y = a^c;
  assign z = d;

  // //Gate-flow modelling
  // wire notc.notb,and1,and2,notd;
  // and(w,b,c);
  // not(notc,c);
  // not(notb,b);
  // and(and1,b,notc);
  // and(and2,a,notb,c);
  // or(x,and1,and2);
  // xor(y,a,c);
  // not(notd,d);
  // not(z,notd);

endmodule

CS247-S1-3_tb.v
module tb();
  reg a,b,c,d;
  wire w,x,y,z;

  bcd dut(
    .a(a),
    .b(b),
    .c(c),
    .d(d),
    .w(w),
    .x(x),
    .y(y),
    .z(z)
  );

  initial begin
    $dumpfile("CS247-S1-3.vcd");
    $dumpvars(0);
    $display("------------------------------");
    $display("A | B | C | D || W | X | Y | Z");
    $monitor("%b | %b | %b | %b || %b | %b | %b | %b",a,b,c,d,w,x,y,z);
  end

  initial begin
    a=1'b0;b=1'b0;c=1'b0;d=1'b0;
    #10;

    a=1'b0;b=1'b0;c=1'b0;d=1'b1;
    #10;

    a=1'b0;b=1'b0;c=1'b1;d=1'b0;
    #10;

    a=1'b0;b=1'b0;c=1'b1;d=1'b1;
    #10;

    a=1'b0;b=1'b1;c=1'b0;d=1'b0;
    #10;

    a=1'b1;b=1'b0;c=1'b1;d=1'b1;
    #10;

    a=1'b1;b=1'b1;c=1'b0;d=1'b0;
    #10;

    a=1'b1;b=1'b1;c=1'b0;d=1'b1;
    #10;

    a=1'b1;b=1'b1;c=1'b1;d=1'b0;
    #10;

    a=1'b1;b=1'b1;c=1'b1;d=1'b1;
    #10;
  
  end

endmodule;

CS247-S1-3.vcd
$date
	Tue Aug 27 01:24:16 2024
$end
$version
	Icarus Verilog
$end
$timescale
	1s
$end
$scope module tb $end
$var wire 1 ! z $end
$var wire 1 " y $end
$var wire 1 # x $end
$var wire 1 $ w $end
$var reg 1 % a $end
$var reg 1 & b $end
$var reg 1 ' c $end
$var reg 1 ( d $end
$scope module dut $end
$var wire 1 % a $end
$var wire 1 & b $end
$var wire 1 ' c $end
$var wire 1 ( d $end
$var wire 1 $ w $end
$var wire 1 # x $end
$var wire 1 " y $end
$var wire 1 ! z $end
$upscope $end
$upscope $end
$enddefinitions $end
$comment Show the parameter values. $end
$dumpall
$end
#0
$dumpvars
0(
0'
0&
0%
0$
0#
0"
0!
$end
#10
1!
1(
#20
1"
0!
0(
1'
#30
1!
1(
#40
1#
0"
0!
0(
0'
1&
#50
1#
1!
1(
1'
0&
1%
#60
1#
1"
0!
0(
0'
1&
#70
1!
1(
#80
0#
1$
0"
0!
0(
1'
#90
1!
1(
